odoo8_addon_stock_quant_merge-8.0.1.0.0.99.dev15-py2.7-nspkg.pth
odoo8_addon_stock_quant_merge-8.0.1.0.0.99.dev15.dist-info/METADATA
odoo8_addon_stock_quant_merge-8.0.1.0.0.99.dev15.dist-info/RECORD
odoo8_addon_stock_quant_merge-8.0.1.0.0.99.dev15.dist-info/WHEEL
odoo8_addon_stock_quant_merge-8.0.1.0.0.99.dev15.dist-info/namespace_packages.txt
odoo8_addon_stock_quant_merge-8.0.1.0.0.99.dev15.dist-info/top_level.txt
odoo_addons/stock_quant_merge/README.rst
odoo_addons/stock_quant_merge/__init__.py
odoo_addons/stock_quant_merge/__openerp__.py
odoo_addons/stock_quant_merge/i18n/de.po
odoo_addons/stock_quant_merge/i18n/es.po
odoo_addons/stock_quant_merge/i18n/fi.po
odoo_addons/stock_quant_merge/i18n/fr.po
odoo_addons/stock_quant_merge/i18n/it.po
odoo_addons/stock_quant_merge/i18n/pt_BR.po
odoo_addons/stock_quant_merge/i18n/sl.po
odoo_addons/stock_quant_merge/i18n/stock_quant_merge.pot
odoo_addons/stock_quant_merge/i18n/zh_CN.po
odoo_addons/stock_quant_merge/models/__init__.py
odoo_addons/stock_quant_merge/models/stock.py
odoo_addons/stock_quant_merge/static/description/icon.png
odoo_addons/stock_quant_merge/tests/__init__.py
odoo_addons/stock_quant_merge/tests/test_merge.py
